lektor_yandex_metrica.py
lektor_yandex_metrica-0.1.2.dist-info/METADATA
lektor_yandex_metrica-0.1.2.dist-info/RECORD
lektor_yandex_metrica-0.1.2.dist-info/WHEEL
lektor_yandex_metrica-0.1.2.dist-info/entry_points.txt
lektor_yandex_metrica-0.1.2.dist-info/top_level.txt
