Metadata-Version: 2.1
Name: lektor-yandex-metrica
Version: 0.1.2
Summary: Adds support for Yandex Metrica to Lektor CMS
Home-page: https://github.com/gagoman/lektor-yandex-metrica
Author: Alex Khomchenko
Author-email: akhomchenko@gmail.com
License: MIT
Keywords: Lektor plugin
Platform: UNKNOWN
Classifier: Development Status :: 3 - Alpha
Classifier: License :: OSI Approved :: MIT License
Classifier: Programming Language :: Python :: 2
Classifier: Programming Language :: Python :: 3
Classifier: Framework :: Lektor
Classifier: Environment :: Plugins
